torchoptix.abi3.so
torchoptix-0.0.1.dist-info/LICENSE
torchoptix-0.0.1.dist-info/METADATA
torchoptix-0.0.1.dist-info/top_level.txt
torchoptix-0.0.1.dist-info/RECORD
torchoptix-0.0.1.dist-info/WHEEL
