Metadata-Version: 2.1
Name: torchoptix
Version: 0.0.1
Summary: Modular python bindings for OptiX.
Home-page: https://github.com/eliphatfs/torchoptix
Author: eliphatfs
Author-email: shiruoxi61@gmail.com
License: UNKNOWN
Platform: UNKNOWN
Classifier: Programming Language :: Python :: 3 :: Only
Classifier: License :: OSI Approved :: Apache Software License
Requires-Python: ~=3.8
License-File: LICENSE
